opn_api/__init__.py
opn_api/exceptions.py
opn_api/api/__init__.py
opn_api/api/base.py
opn_api/api/client.py
opn_api/api/core/__init__.py
opn_api/api/core/configbackup.py
opn_api/api/core/dhcp.py
opn_api/api/core/dhcp_v4.py
opn_api/api/core/firewall.py
opn_api/api/core/firmware.py
opn_api/api/core/ipsec.py
opn_api/api/core/routes.py
opn_api/api/core/syslog.py
opn_api/api/core/unbound.py
opn_api/api/plugin/__init__.py
opn_api/api/plugin/apibackup.py
opn_api/api/plugin/haproxy.py
opn_api/api/plugin/nodeexporter.py
opn_api/api/plugin/openvpn.py
opn_api/client/__init__.py
opn_api/client/client.py
opn_api/client/controllers/__init__.py
opn_api/client/controllers/alias_controller.py
opn_api/client/controllers/dhcp_controller.py
opn_api/client/controllers/filter_controller.py
opn_api/models/__init__.py
opn_api/models/dhcp.py
opn_api/models/firewall_alias.py
opn_api/models/firewall_models.py
opn_api/util/__init__.py
opn_api/util/parse.py
opn_api/util/validate.py
opn_api-0.5.0.dist-info/METADATA
opn_api-0.5.0.dist-info/WHEEL
opn_api-0.5.0.dist-info/licenses/LICENSE
opn_api-0.5.0.dist-info/RECORD
