Metadata-Version: 2.4
Name: opn-api
Version: 0.5.0
Summary: A Python client library for OPNsense API.
Project-URL: homepage, https://github.com/devinbarry/opn-api
Project-URL: repository, https://github.com/devinbarry/opn-api
Project-URL: documentation, https://github.com/devinbarry/opn-api
Author: Andreas Stürz
Author-email: Devin Barry <devinbarry@users.noreply.github.com>, Dylan Turnbull <dylanturn@gmail.com>
License:                     GNU AFFERO GENERAL PUBLIC LICENSE
License-File: LICENSE
Keywords: API,OPNsense
Classifier: Development Status :: 4 - Beta
Classifier: Intended Audience :: Developers
Classifier: Programming Language :: Python :: 3
Classifier: Programming Language :: Python :: 3.11
Classifier: Programming Language :: Python :: 3.12
Classifier: Programming Language :: Python :: 3.13
Classifier: Topic :: Software Development :: Libraries :: Python Modules
Requires-Python: >=3.11
Requires-Dist: arrow
Requires-Dist: pydantic
Requires-Dist: requests
Provides-Extra: dev
Requires-Dist: pytest; extra == 'dev'
Requires-Dist: python-dotenv; extra == 'dev'
Requires-Dist: ruff; extra == 'dev'
